[{"userId":"__global__","key":"character_events","value":[]},{"userId":"__global__","key":"character_statuses","value":{}},{"userId":"__global__","key":"character_todos","value":[]},{"userId":"__global__","key":"gen_template_138b0ad1-e642-4cd5-9baf-26803dc76497","value":""},{"userId":"__global__","key":"gen_template_ab6175f0-579c-44c0-8fca-2d468c0a4316","value":""},{"userId":"__global__","key":"gen_template_edd761ca-a03f-44d5-a231-f86849ee912c","value":""},{"userId":"uid_1775576390275_wj1f7m1mq","key":"customHolidays","value":{}},{"userId":"uid_1775576390275_wj1f7m1mq","key":"enabledCountries","value":["CN"]},{"userId":"uid_1775576390275_wj1f7m1mq","key":"events","value":[]},{"userId":"uid_1775576390275_wj1f7m1mq","key":"markers","value":{}},{"userId":"uid_1775576390275_wj1f7m1mq","key":"moods","value":{}},{"userId":"uid_1775576390275_wj1f7m1mq","key":"todos","value":[]},{"userId":"uid_1775659284737_35u0yhbun","key":"customHolidays","value":{}},{"userId":"uid_1775659284737_35u0yhbun","key":"enabledCountries","value":["CN"]},{"userId":"uid_1775659284737_35u0yhbun","key":"events","value":[]},{"userId":"uid_1775659284737_35u0yhbun","key":"markers","value":{}},{"userId":"uid_1775659284737_35u0yhbun","key":"moods","value":{}},{"userId":"uid_1775659284737_35u0yhbun","key":"todos","value":[]},{"userId":"uid_1775757069116_pnzrl5ekv","key":"customHolidays","value":{}},{"userId":"uid_1775757069116_pnzrl5ekv","key":"enabledCountries","value":["CN"]},{"userId":"uid_1775757069116_pnzrl5ekv","key":"events","value":[]},{"userId":"uid_1775757069116_pnzrl5ekv","key":"markers","value":{}},{"userId":"uid_1775757069116_pnzrl5ekv","key":"moods","value":{}},{"userId":"uid_1775757069116_pnzrl5ekv","key":"todos","value":[]}]