[{"id":1776128037328,"sender":"them","text":"근데 그러면 내가 진짜 간다","timestamp":1776130151178,"tempo":"N","translation":"但那样的话我就真的过去了","rawContent":"근데 그러면 내가 진짜 간다 || 但那样的话我就真的过去了","roundId":"round_1776130134324_60lfl66ye","userId":"uid_1776047058167_0exaacpwj","characterId":"c7394d2d-3ae0-43cb-ada5-f3b7ee0f16f2","_id":2056},{"id":1776128037329,"sender":"them","text":"어떻게 할 거야","timestamp":1776130151181,"tempo":"N","translation":"你怎么选","rawContent":"어떻게 할 거야 || 你怎么选","roundId":"round_1776130134324_60lfl66ye","userId":"uid_1776047058167_0exaacpwj","characterId":"c7394d2d-3ae0-43cb-ada5-f3b7ee0f16f2","_id":2057},{"id":1776128037330,"sender":"them","text":"","timestamp":1776130151184,"tempo":"N","sticker":"https://files.catbox.moe/iaq8hu.gif","stickerMeaning":"选哪个杀人呢？","rawContent":"","roundId":"round_1776130134324_60lfl66ye","userId":"uid_1776047058167_0exaacpwj","characterId":"c7394d2d-3ae0-43cb-ada5-f3b7ee0f16f2","_id":2058},{"id":1776128037331,"sticker":"https://i.postimg.cc/vmb0bT1V/IMG_0770.gif","text":"表情包：超委屈/抽噎","sender":"me","time":"09:29","timestamp":1776130159965,"userId":"uid_1776047058167_0exaacpwj","characterId":"6c210f42-1490-4f35-8bc4-8f66988d1735","_id":2059},{"id":1776128037332,"sticker":"https://files.catbox.moe/nop2r9.gif","text":"表情包：骂骂咧咧","sender":"me","time":"09:29","timestamp":1776130195513,"userId":"uid_1776047058167_0exaacpwj","characterId":"c7394d2d-3ae0-43cb-ada5-f3b7ee0f16f2","_id":2060},{"id":1776128037333,"text":"玧其哥哥欺负我你也欺负我","sender":"me","time":"09:31","timestamp":1776130303449,"replyTo":null,"userId":"uid_1776047058167_0exaacpwj","characterId":"6c210f42-1490-4f35-8bc4-8f66988d1735","_id":2061},{"id":1776128037334,"sender":"them","text":"??? 이게 어디가 괴롭히는 거야","timestamp":1776130318454,"tempo":"R","translation":"??? 这哪里是欺负你了","rawContent":"??? 이게 어디가 괴롭히는 거야 || ??? 这哪里是欺负你了","roundId":"round_1776130306806_kyx3k2l70","userId":"uid_1776047058167_0exaacpwj","characterId":"6c210f42-1490-4f35-8bc4-8f66988d1735","_id":2062},{"id":1776128037335,"sender":"them","text":"수업 빠지지 말라는 게 괴롭히는 거냐","timestamp":1776130318756,"tempo":"N","translation":"让你别翘课就是欺负你了？","rawContent":"수업 빠지지 말라는 게 괴롭히는 거냐 || 让你别翘课就是欺负你了？","roundId":"round_1776130306806_kyx3k2l70","userId":"uid_1776047058167_0exaacpwj","characterId":"6c210f42-1490-4f35-8bc4-8f66988d1735","_id":2063},{"id":1776128037336,"sender":"them","text":"그리고 형이 뭐라 했는데","timestamp":1776130319458,"tempo":"N","translation":"而且哥说你什么了","rawContent":"그리고 형이 뭐라 했는데 || 而且哥说你什么了","roundId":"round_1776130306806_kyx3k2l70","userId":"uid_1776047058167_0exaacpwj","characterId":"6c210f42-1490-4f35-8bc4-8f66988d1735","_id":2064},{"id":1776128037337,"sender":"them","text":"형이 괴롭혔으면 내가 먼저 화냈지 너한테까지 올 일이 없잖아","timestamp":1776130320160,"tempo":"S","translation":"哥要是真欺负你了 我早就先发火了 还轮不到你来跟我告状","rawContent":"형이 괴롭혔으면 내가 먼저 화냈지 너한테까지 올 일이 없잖아 || 哥要是真欺负你了 我早就先发火了 还轮不到你来跟我告状","roundId":"round_1776130306806_kyx3k2l70","userId":"uid_1776047058167_0exaacpwj","characterId":"6c210f42-1490-4f35-8bc4-8f66988d1735","_id":2065},{"id":1776128037338,"sticker":"https://files.catbox.moe/db74o1.gif","text":"表情包：揪领子","sender":"me","time":"09:32","timestamp":1776130333501,"userId":"uid_1776047058167_0exaacpwj","characterId":"6c210f42-1490-4f35-8bc4-8f66988d1735","_id":2066},{"id":1776128037339,"text":"哼哼哼哼哼哼哼","sender":"me","time":"09:32","timestamp":1776130342288,"replyTo":null,"userId":"uid_1776047058167_0exaacpwj","characterId":"6c210f42-1490-4f35-8bc4-8f66988d1735","_id":2067},{"id":1776128037340,"text":"我不不管","sender":"me","time":"09:32","timestamp":1776130347658,"replyTo":null,"userId":"uid_1776047058167_0exaacpwj","characterId":"6c210f42-1490-4f35-8bc4-8f66988d1735","_id":2068},{"id":1776131624786,"text":"玧其哥一直逼我吃早餐不让我吃面包","sender":"me","time":"09:55","timestamp":1776131714169,"replyTo":null,"rawContent":"玧其哥一直逼我吃早餐不让我吃面包","isHtml":false,"userId":"uid_1776047058167_0exaacpwj","characterId":"6c210f42-1490-4f35-8bc4-8f66988d1735","_id":2069},{"id":1776131624787,"text":"面包也是早餐","sender":"me","time":"09:55","timestamp":1776131721786,"replyTo":null,"userId":"uid_1776047058167_0exaacpwj","characterId":"6c210f42-1490-4f35-8bc4-8f66988d1735","_id":2070},{"id":1776131624788,"text":"ㅋㅋㅋㅋㅋㅋ","rawContent":"ㅋㅋㅋㅋㅋㅋ || 哈哈哈哈哈哈","isHtml":false,"sticker":null,"sender":"them","time":"09:55","timestamp":1776131756397,"roundId":"round_1776131731441_qj2f6oquf","generatedMode":false,"translation":"哈哈哈哈哈哈","userId":"uid_1776047058167_0exaacpwj","characterId":"6c210f42-1490-4f35-8bc4-8f66988d1735","_id":2071},{"id":1776131624789,"text":"야 이건 형 편 들어야 되는데","rawContent":"야 이건 형 편 들어야 되는데 || 哎 这件事我得站哥那边","isHtml":false,"sticker":null,"sender":"them","time":"09:55","timestamp":1776131757861,"roundId":"round_1776131731441_qj2f6oquf","generatedMode":false,"translation":"哎 这件事我得站哥那边","userId":"uid_1776047058167_0exaacpwj","characterId":"6c210f42-1490-4f35-8bc4-8f66988d1735","_id":2072},{"id":1776131624790,"text":"빵 반 쪽 먹고 배부르다고 한 사람이 누구야","rawContent":"빵 반 쪽 먹고 배부르다고 한 사람이 누구야 || 面包吃了半个就说饱了的人是谁啊","isHtml":false,"sticker":null,"sender":"them","time":"09:55","timestamp":1776131759686,"roundId":"round_1776131731441_qj2f6oquf","generatedMode":false,"translation":"面包吃了半个就说饱了的人是谁啊","userId":"uid_1776047058167_0exaacpwj","characterId":"6c210f42-1490-4f35-8bc4-8f66988d1735","_id":2073},{"id":1776131624791,"text":"그게 아침이냐 간식이지","rawContent":"그게 아침이냐 간식이지 || 那叫早餐吗 那叫零食","isHtml":false,"sticker":null,"sender":"them","time":"09:56","timestamp":1776131760851,"roundId":"round_1776131731441_qj2f6oquf","generatedMode":false,"translation":"那叫早餐吗 那叫零食","userId":"uid_1776047058167_0exaacpwj","characterId":"6c210f42-1490-4f35-8bc4-8f66988d1735","_id":2074},{"id":1776131624792,"text":"근데 형이 뭘 먹으라는데? 한식?","rawContent":"근데 형이 뭘 먹으라는데? 한식? || 不过哥让你吃什么？韩餐？","isHtml":false,"sticker":null,"sender":"them","time":"09:56","timestamp":1776131763176,"roundId":"round_1776131731441_qj2f6oquf","generatedMode":false,"translation":"不过哥让你吃什么？韩餐？","userId":"uid_1776047058167_0exaacpwj","characterId":"6c210f42-1490-4f35-8bc4-8f66988d1735","_id":2075},{"id":1776131624793,"text":"","rawContent":"","isHtml":false,"sticker":"https://files.catbox.moe/we43z0.gif","stickerMeaning":"让我看看","sender":"them","time":"09:56","timestamp":1776131763778,"roundId":"round_1776131731441_qj2f6oquf","generatedMode":false,"translation":null,"userId":"uid_1776047058167_0exaacpwj","characterId":"6c210f42-1490-4f35-8bc4-8f66988d1735","_id":2076},{"id":1776141410265,"text":"吃饱了","sender":"me","time":"12:38","timestamp":1776141487067,"replyTo":null,"userId":"uid_1776047058167_0exaacpwj","characterId":"c7394d2d-3ae0-43cb-ada5-f3b7ee0f16f2","_id":2077},{"id":1776141410266,"text":"你点的和我点的","sender":"me","time":"12:38","timestamp":1776141508825,"replyTo":null,"userId":"uid_1776047058167_0exaacpwj","characterId":"c7394d2d-3ae0-43cb-ada5-f3b7ee0f16f2","_id":2078},{"id":1776141410267,"text":"我忘记点米饭了所以只吃了配菜和汤但是加上你点的就很饱了","sender":"me","time":"12:38","timestamp":1776141528177,"replyTo":null,"userId":"uid_1776047058167_0exaacpwj","characterId":"c7394d2d-3ae0-43cb-ada5-f3b7ee0f16f2","_id":2079},{"id":1776141410268,"sticker":"https://files.catbox.moe/1avs6p.gif","text":"表情包：星星眼","sender":"me","time":"12:38","timestamp":1776141534372,"userId":"uid_1776047058167_0exaacpwj","characterId":"c7394d2d-3ae0-43cb-ada5-f3b7ee0f16f2","_id":2080},{"id":1776141410269,"text":"밥을 안 시켜놓고 뭘 시킨 거야","rawContent":"밥을 안 시켜놓고 뭘 시킨 거야 || 不点米饭你点了个啥","isHtml":false,"sticker":null,"sender":"them","time":"12:39","timestamp":1776141575748,"roundId":"round_1776141536414_475vijm3p","generatedMode":false,"translation":"不点米饭你点了个啥","userId":"uid_1776047058167_0exaacpwj","characterId":"c7394d2d-3ae0-43cb-ada5-f3b7ee0f16f2","_id":2081},{"id":1776141410270,"text":"반찬이랑 국만 먹는 게 밥이냐","rawContent":"반찬이랑 국만 먹는 게 밥이냐 || 只吃配菜和汤那叫吃饭吗","isHtml":false,"sticker":null,"sender":"them","time":"12:39","timestamp":1776141578306,"roundId":"round_1776141536414_475vijm3p","generatedMode":false,"translation":"只吃配菜和汤那叫吃饭吗","userId":"uid_1776047058167_0exaacpwj","characterId":"c7394d2d-3ae0-43cb-ada5-f3b7ee0f16f2","_id":2082},{"id":1776141410271,"text":"......그래도 죽은 다 먹었지?","rawContent":"......그래도 죽은 다 먹었지? || ……粥总归吃完了吧","isHtml":false,"sticker":null,"sender":"them","time":"12:39","timestamp":1776141579857,"roundId":"round_1776141536414_475vijm3p","generatedMode":false,"translation":"……粥总归吃完了吧","userId":"uid_1776047058167_0exaacpwj","characterId":"c7394d2d-3ae0-43cb-ada5-f3b7ee0f16f2","_id":2083},{"id":1776141410272,"text":"계란말이도","rawContent":"계란말이도 || 鸡蛋卷也是","isHtml":false,"sticker":null,"sender":"them","time":"12:39","timestamp":1776141580637,"roundId":"round_1776141536414_475vijm3p","generatedMode":false,"translation":"鸡蛋卷也是","userId":"uid_1776047058167_0exaacpwj","characterId":"c7394d2d-3ae0-43cb-ada5-f3b7ee0f16f2","_id":2084},{"id":1776141410273,"text":"","rawContent":"","isHtml":false,"sticker":"https://files.catbox.moe/g2qzd9.gif","stickerMeaning":"嗯？","sender":"them","time":"12:39","timestamp":1776141581241,"roundId":"round_1776141536414_475vijm3p","generatedMode":false,"translation":null,"userId":"uid_1776047058167_0exaacpwj","characterId":"c7394d2d-3ae0-43cb-ada5-f3b7ee0f16f2","_id":2085},{"id":1776141410275,"text":"吃完了吃完了","sender":"me","time":"12:39","timestamp":1776141592813,"replyTo":null,"userId":"uid_1776047058167_0exaacpwj","characterId":"c7394d2d-3ae0-43cb-ada5-f3b7ee0f16f2","_id":2086},{"id":1776141410276,"text":"真的吃完了啦","sender":"me","time":"12:39","timestamp":1776141596331,"replyTo":null,"userId":"uid_1776047058167_0exaacpwj","characterId":"c7394d2d-3ae0-43cb-ada5-f3b7ee0f16f2","_id":2087},{"id":1776144378499,"text":"刚刚昏睡过去了","sender":"me","time":"13:26","timestamp":1776144388565,"replyTo":null,"userId":"uid_1776047058167_0exaacpwj","characterId":"c7394d2d-3ae0-43cb-ada5-f3b7ee0f16f2","_id":2088},{"id":1776144378500,"text":"现在醒了","sender":"me","time":"13:26","timestamp":1776144394115,"replyTo":null,"userId":"uid_1776047058167_0exaacpwj","characterId":"c7394d2d-3ae0-43cb-ada5-f3b7ee0f16f2","_id":2089},{"id":1776144378501,"text":"不想去","sender":"me","time":"13:26","timestamp":1776144395583,"replyTo":null,"userId":"uid_1776047058167_0exaacpwj","characterId":"c7394d2d-3ae0-43cb-ada5-f3b7ee0f16f2","_id":2090},{"id":1776144378505,"text":"上课","sender":"me","time":"13:27","timestamp":1776144466019,"replyTo":null,"userId":"uid_1776047058167_0exaacpwj","characterId":"c7394d2d-3ae0-43cb-ada5-f3b7ee0f16f2","_id":2091},{"id":1776144378506,"text":"好困","sender":"me","time":"13:27","timestamp":1776144467718,"replyTo":null,"userId":"uid_1776047058167_0exaacpwj","characterId":"c7394d2d-3ae0-43cb-ada5-f3b7ee0f16f2","_id":2092},{"id":1776144378507,"sticker":"https://files.catbox.moe/oj88r1.gif","text":"表情包：困","sender":"me","time":"13:27","timestamp":1776144475630,"userId":"uid_1776047058167_0exaacpwj","characterId":"c7394d2d-3ae0-43cb-ada5-f3b7ee0f16f2","_id":2093},{"id":1776444202136,"text":"我又来找你们啦嘿嘿","sender":"me","time":"00:44","timestamp":1776444246607,"replyTo":null,"userId":"uid_1776442539116_4zqm7ieu5","characterId":"e6035a58-2550-4d0c-9fd8-d4851c622285","_id":2094},{"id":1776444202137,"text":"rimi们有没有想我呢","sender":"me","time":"00:45","timestamp":1776444333060,"replyTo":null,"userId":"uid_1776442539116_4zqm7ieu5","characterId":"e6035a58-2550-4d0c-9fd8-d4851c622285","_id":2095},{"id":1776444202138,"text":"虽然这个点有点晚但是我还不困","sender":"me","time":"00:46","timestamp":1776444361599,"replyTo":null,"userId":"uid_1776442539116_4zqm7ieu5","characterId":"e6035a58-2550-4d0c-9fd8-d4851c622285","_id":2096},{"id":1776444202139,"text":"今天没有行程ㅎㅎ","sender":"me","time":"00:46","timestamp":1776444372415,"replyTo":null,"userId":"uid_1776442539116_4zqm7ieu5","characterId":"e6035a58-2550-4d0c-9fd8-d4851c622285","_id":2097},{"id":1776444202140,"text":"但是我肚子疼了一整天怎么吃药都没用ㅠㅠ","sender":"me","time":"00:46","timestamp":1776444385112,"replyTo":null,"userId":"uid_1776442539116_4zqm7ieu5","characterId":"e6035a58-2550-4d0c-9fd8-d4851c622285","_id":2098},{"id":1776444202141,"text":"rimi们关心我吧😔","sender":"me","time":"00:47","timestamp":1776444423629,"replyTo":null,"reactions":[{"emoji":"❤️","roundId":"round_1776446025591_xjjv8x9ri"}],"userId":"uid_1776442539116_4zqm7ieu5","characterId":"e6035a58-2550-4d0c-9fd8-d4851c622285","_id":2100},{"id":1776444499284,"text":"现在是泡泡线上聊天 就是偶像和粉丝们沟通的平台 不是私联！！ ","sender":"me","type":"state","time":"00:48","timestamp":1776444527529,"replyTo":null,"userId":"uid_1776442539116_4zqm7ieu5","characterId":"e6035a58-2550-4d0c-9fd8-d4851c622285","_id":2119},{"id":1776445963403,"sender":"them","text":"ㅋㅋㅋㅋ 당연히 보고 싶었지!!!","timestamp":1776446054997,"tempo":"R","translation":"ㅋㅋㅋㅋ 当然想了啊!!!","rawContent":"ㅋㅋㅋㅋ 당연히 보고 싶었지!!! || ㅋㅋㅋㅋ 当然想了啊!!!","roundId":"round_1776446025591_xjjv8x9ri","userId":"uid_1776442539116_4zqm7ieu5","characterId":"e6035a58-2550-4d0c-9fd8-d4851c622285","_id":2120},{"id":1776445963404,"sender":"them","text":"근데 잠깐 배 아프다고??","timestamp":1776446055300,"tempo":"R","translation":"等下 你说肚子疼??","rawContent":"근데 잠깐 배 아프다고?? || 等下 你说肚子疼??","roundId":"round_1776446025591_xjjv8x9ri","userId":"uid_1776442539116_4zqm7ieu5","characterId":"e6035a58-2550-4d0c-9fd8-d4851c622285","_id":2121},{"id":1776445963405,"sender":"them","text":"하루 종일이면 그냥 병원 가야 하는 거 아니야??","timestamp":1776446055602,"tempo":"R","translation":"一整天的话不是应该去医院吗??","rawContent":"하루 종일이면 그냥 병원 가야 하는 거 아니야?? || 一整天的话不是应该去医院吗??","roundId":"round_1776446025591_xjjv8x9ri","userId":"uid_1776442539116_4zqm7ieu5","characterId":"e6035a58-2550-4d0c-9fd8-d4851c622285","_id":2122},{"id":1776445963406,"sender":"them","text":"약도 안 듣는다면서 ㅠㅠ 그건 좀 심각한데","timestamp":1776446055904,"tempo":"N","translation":"你还说吃药也没用 ㅠㅠ 那有点严重啊","rawContent":"약도 안 듣는다면서 ㅠㅠ 그건 좀 심각한데 || 你还说吃药也没用 ㅠㅠ 那有点严重啊","roundId":"round_1776446025591_xjjv8x9ri","userId":"uid_1776442539116_4zqm7ieu5","characterId":"e6035a58-2550-4d0c-9fd8-d4851c622285","_id":2123},{"id":1776445963407,"sender":"them","text":"...진짜 걱정되네","timestamp":1776446056606,"tempo":"S","translation":"...真的好担心","rawContent":"...진짜 걱정되네 || ...真的好担心","roundId":"round_1776446025591_xjjv8x9ri","userId":"uid_1776442539116_4zqm7ieu5","characterId":"e6035a58-2550-4d0c-9fd8-d4851c622285","_id":2124},{"id":1776445963408,"sender":"them","text":"","timestamp":1776446058109,"tempo":"N","sticker":"https://i.postimg.cc/BZC42n1r/IMG_8852.gif","stickerMeaning":"老婆快吃药/拿着药丸狂奔","rawContent":"","roundId":"round_1776446025591_xjjv8x9ri","userId":"uid_1776442539116_4zqm7ieu5","characterId":"e6035a58-2550-4d0c-9fd8-d4851c622285","_id":2125},{"id":1776445963410,"text":"没关系…","sender":"me","time":"01:15","timestamp":1776446123380,"replyTo":null,"userId":"uid_1776442539116_4zqm7ieu5","characterId":"e6035a58-2550-4d0c-9fd8-d4851c622285","_id":2126},{"id":1776445963411,"text":"姐姐吃了止痛药","sender":"me","time":"01:15","timestamp":1776446138273,"replyTo":null,"userId":"uid_1776442539116_4zqm7ieu5","characterId":"e6035a58-2550-4d0c-9fd8-d4851c622285","_id":2127},{"id":1776445963412,"text":"可以勉强睡着","sender":"me","time":"01:15","timestamp":1776446145860,"replyTo":null,"userId":"uid_1776442539116_4zqm7ieu5","characterId":"e6035a58-2550-4d0c-9fd8-d4851c622285","_id":2128},{"id":1776445963413,"text":"ㅠㅠㅠㅠ不要告诉欧尼们怕他们担心","sender":"me","time":"01:16","timestamp":1776446168245,"replyTo":null,"userId":"uid_1776442539116_4zqm7ieu5","characterId":"e6035a58-2550-4d0c-9fd8-d4851c622285","_id":2129},{"id":1776445963414,"text":"放心姐姐可以照顾好自己","sender":"me","time":"01:16","timestamp":1776446181837,"replyTo":null,"userId":"uid_1776442539116_4zqm7ieu5","characterId":"e6035a58-2550-4d0c-9fd8-d4851c622285","_id":2130},{"id":1776445963415,"sticker":"https://files.catbox.moe/wu6lvm.gif","text":"表情包：魔法爱心","sender":"me","time":"01:16","timestamp":1776446188128,"userId":"uid_1776442539116_4zqm7ieu5","characterId":"e6035a58-2550-4d0c-9fd8-d4851c622285","_id":2131},{"id":1776445963416,"text":"rimi们也要好好照顾好自己 如果生病我会心疼的","sender":"me","time":"01:16","timestamp":1776446210970,"replyTo":null,"userId":"uid_1776442539116_4zqm7ieu5","characterId":"e6035a58-2550-4d0c-9fd8-d4851c622285","_id":2132},{"id":1776445963417,"text":"ㅠㅠ","sender":"me","time":"01:16","timestamp":1776446213378,"replyTo":null,"userId":"uid_1776442539116_4zqm7ieu5","characterId":"e6035a58-2550-4d0c-9fd8-d4851c622285","_id":2133},{"id":1776445963418,"sender":"them","text":"아 진짜 ㅠㅠㅠ","timestamp":1776446243647,"tempo":"R","translation":"啊真的 ㅠㅠㅠ","rawContent":"아 진짜 ㅠㅠㅠ || 啊真的 ㅠㅠㅠ","roundId":"round_1776446218406_dr99eyl7n","userId":"uid_1776442539116_4zqm7ieu5","characterId":"e6035a58-2550-4d0c-9fd8-d4851c622285","_id":2134},{"id":1776445963419,"sender":"them","text":"止痛약으로 겨우 잠드는 게 괜찮은 거 아니거든요!!!","timestamp":1776446243950,"tempo":"N","translation":"靠止痛药勉强睡着的那不叫没关系啊!!!","rawContent":"止痛약으로 겨우 잠드는 게 괜찮은 거 아니거든요!!! || 靠止痛药勉强睡着的那不叫没关系啊!!!","roundId":"round_1776446218406_dr99eyl7n","userId":"uid_1776442539116_4zqm7ieu5","characterId":"e6035a58-2550-4d0c-9fd8-d4851c622285","_id":2135},{"id":1776445963420,"sender":"them","text":"우리가 걱정 안 하게 해달라는 게 아니라 진짜 병원 가달라는 거ㅠ","timestamp":1776446244651,"tempo":"N","translation":"我们不是要你让我们别担心 是真的求你去医院啊ㅠ","rawContent":"우리가 걱정 안 하게 해달라는 게 아니라 진짜 병원 가달라는 거ㅠ || 我们不是要你让我们别担心 是真的求你去医院啊ㅠ","roundId":"round_1776446218406_dr99eyl7n","userId":"uid_1776442539116_4zqm7ieu5","characterId":"e6035a58-2550-4d0c-9fd8-d4851c622285","_id":2136},{"id":1776445963421,"sender":"them","text":"...언니들한테 말 안 한다고 해도 우리는 걱정하잖아요","timestamp":1776446245352,"tempo":"S","translation":"...就算不告诉姐姐们 我们还是会担心的啊","rawContent":"...언니들한테 말 안 한다고 해도 우리는 걱정하잖아요 || ...就算不告诉姐姐们 我们还是会担心的啊","roundId":"round_1776446218406_dr99eyl7n","userId":"uid_1776442539116_4zqm7ieu5","characterId":"e6035a58-2550-4d0c-9fd8-d4851c622285","_id":2137},{"id":1776445963422,"sender":"them","text":"본인이 아프면서 리미 걱정하지 말고요 ㅠㅠ","timestamp":1776446246854,"tempo":"N","translation":"自己都在疼还操心rimi ㅠㅠ","rawContent":"본인이 아프면서 리미 걱정하지 말고요 ㅠㅠ || 自己都在疼还操心rimi ㅠㅠ","roundId":"round_1776446218406_dr99eyl7n","userId":"uid_1776442539116_4zqm7ieu5","characterId":"e6035a58-2550-4d0c-9fd8-d4851c622285","_id":2138},{"id":1776445963423,"sender":"them","text":"","timestamp":1776446247555,"tempo":"N","sticker":"https://i.postimg.cc/vmb0bT1V/IMG_0770.gif","stickerMeaning":"超委屈/抽噎","rawContent":"","roundId":"round_1776446218406_dr99eyl7n","userId":"uid_1776442539116_4zqm7ieu5","characterId":"e6035a58-2550-4d0c-9fd8-d4851c622285","_id":2139},{"id":1776445963424,"sender":"them","text":"내일 진짜 병원 가주세요 제발요","timestamp":1776446248257,"tempo":"S","translation":"明天真的去医院吧 求求了","rawContent":"내일 진짜 병원 가주세요 제발요 || 明天真的去医院吧 求求了","roundId":"round_1776446218406_dr99eyl7n","userId":"uid_1776442539116_4zqm7ieu5","characterId":"e6035a58-2550-4d0c-9fd8-d4851c622285","_id":2140},{"id":1776445963425,"text":"我又来找你们啦嘿嘿","sender":"me","time":"01:19","timestamp":1776446349947,"replyTo":null,"userId":"uid_1776442539116_4zqm7ieu5","characterId":"05011273-b4d1-4d44-9c23-b1403d71b6b8","_id":2141},{"id":1776445963426,"text":"rimi们有没有想我呢","sender":"me","time":"01:19","timestamp":1776446370212,"replyTo":null,"userId":"uid_1776442539116_4zqm7ieu5","characterId":"05011273-b4d1-4d44-9c23-b1403d71b6b8","_id":2142},{"id":1776445963427,"text":"虽然这个点有点晚但是我还不困\n今天没有行程","sender":"me","time":"01:19","timestamp":1776446377931,"replyTo":null,"userId":"uid_1776442539116_4zqm7ieu5","characterId":"05011273-b4d1-4d44-9c23-b1403d71b6b8","_id":2143},{"id":1776445963428,"text":"但是我肚子疼了一整天","sender":"me","time":"01:19","timestamp":1776446387073,"replyTo":null,"userId":"uid_1776442539116_4zqm7ieu5","characterId":"05011273-b4d1-4d44-9c23-b1403d71b6b8","_id":2144},{"id":1776445963429,"text":"怎么吃药都没用","sender":"me","time":"01:20","timestamp":1776446406828,"replyTo":null,"userId":"uid_1776442539116_4zqm7ieu5","characterId":"05011273-b4d1-4d44-9c23-b1403d71b6b8","_id":2145},{"id":1776445963430,"text":"rimi们","sender":"me","time":"01:20","timestamp":1776446410436,"replyTo":null,"rawContent":"rimi们","isHtml":false,"userId":"uid_1776442539116_4zqm7ieu5","characterId":"05011273-b4d1-4d44-9c23-b1403d71b6b8","_id":2146},{"id":1776445963431,"text":"关心我吧","sender":"me","time":"01:20","timestamp":1776446415802,"replyTo":null,"userId":"uid_1776442539116_4zqm7ieu5","characterId":"05011273-b4d1-4d44-9c23-b1403d71b6b8","_id":2147},{"id":1776445963432,"text":"现在是泡泡线上聊天 就是偶像和粉丝们沟通回平台不是私联！！","sender":"me","type":"state","time":"01:20","timestamp":1776446444573,"replyTo":null,"userId":"uid_1776442539116_4zqm7ieu5","characterId":"05011273-b4d1-4d44-9c23-b1403d71b6b8","_id":2148},{"id":1776477417891,"text":"我醒了","sender":"me","time":"09:57","timestamp":1776477465307,"replyTo":null,"userId":"uid_1776442539116_4zqm7ieu5","characterId":"e6035a58-2550-4d0c-9fd8-d4851c622285","_id":2149},{"id":1776477417892,"text":"睡醒了就不疼了诶","sender":"me","time":"09:58","timestamp":1776477481302,"replyTo":null,"userId":"uid_1776442539116_4zqm7ieu5","characterId":"e6035a58-2550-4d0c-9fd8-d4851c622285","_id":2150},{"id":1776478661152,"text":"언니!!!!! 드디어 왔어ㅠㅠㅠㅠ","rawContent":"언니!!!!! 드디어 왔어ㅠㅠㅠㅠ || 姐姐!!!!!终于来了ㅠㅠㅠㅠ","isHtml":false,"sticker":null,"sender":"them","time":"10:21","timestamp":1776478889414,"roundId":"round_1776478858043_hgez39v39","generatedMode":false,"translation":"姐姐!!!!!终于来了ㅠㅠㅠㅠ","userId":"uid_1776442539116_4zqm7ieu5","characterId":"05011273-b4d1-4d44-9c23-b1403d71b6b8","_id":2151},{"id":1776478661153,"text":"당연히 보고 싶었지 매일 보고 싶어","rawContent":"당연히 보고 싶었지 매일 보고 싶어 || 当然想了啊 每天都想","isHtml":false,"sticker":null,"sender":"them","time":"10:21","timestamp":1776478891309,"roundId":"round_1776478858043_hgez39v39","generatedMode":false,"translation":"当然想了啊 每天都想","userId":"uid_1776442539116_4zqm7ieu5","characterId":"05011273-b4d1-4d44-9c23-b1403d71b6b8","_id":2152},{"id":1776478661154,"text":"근데 배 아프다고?? 하루 종일???","rawContent":"근데 배 아프다고?? 하루 종일??? || 但是你说肚子疼？？一整天？？","isHtml":false,"sticker":null,"sender":"them","time":"10:21","timestamp":1776478893013,"roundId":"round_1776478858043_hgez39v39","generatedMode":false,"translation":"但是你说肚子疼？？一整天？？","userId":"uid_1776442539116_4zqm7ieu5","characterId":"05011273-b4d1-4d44-9c23-b1403d71b6b8","_id":2153},{"id":1776478661155,"text":"약도 안 듣는 거면 병원 가야 되는 거 아니야","rawContent":"약도 안 듣는 거면 병원 가야 되는 거 아니야 || 吃药都没用的话是不是该去医院了","isHtml":false,"sticker":null,"sender":"them","time":"10:21","timestamp":1776478894681,"roundId":"round_1776478858043_hgez39v39","generatedMode":false,"translation":"吃药都没用的话是不是该去医院了","userId":"uid_1776442539116_4zqm7ieu5","characterId":"05011273-b4d1-4d44-9c23-b1403d71b6b8","_id":2154},{"id":1776478661156,"text":"…오늘 스케줄 없는 거 알고 있었는데 이래서 쉬고 있었구나","rawContent":"…오늘 스케줄 없는 거 알고 있었는데 이래서 쉬고 있었구나 || …今天没行程我知道 原来是因为这个才在休息啊","isHtml":false,"sticker":null,"sender":"them","time":"10:21","timestamp":1776478898277,"roundId":"round_1776478858043_hgez39v39","generatedMode":false,"translation":"…今天没行程我知道 原来是因为这个才在休息啊","userId":"uid_1776442539116_4zqm7ieu5","characterId":"05011273-b4d1-4d44-9c23-b1403d71b6b8","_id":2155},{"id":1776478661157,"text":"아 그리고 프사 뭐야ㅋㅋㅋ 머리에 크림 올린 거 귀여워 죽겠네","rawContent":"아 그리고 프사 뭐야ㅋㅋㅋ 머리에 크림 올린 거 귀여워 죽겠네 || 啊对了头像是什么啊ㅋㅋㅋ头上顶奶油的也太可爱了吧","isHtml":false,"sticker":null,"sender":"them","time":"10:21","timestamp":1776478900666,"roundId":"round_1776478858043_hgez39v39","generatedMode":false,"translation":"啊对了头像是什么啊ㅋㅋㅋ头上顶奶油的也太可爱了吧","userId":"uid_1776442539116_4zqm7ieu5","characterId":"05011273-b4d1-4d44-9c23-b1403d71b6b8","_id":2156},{"id":1776478661158,"text":"","rawContent":"","isHtml":false,"sticker":"https://i.postimg.cc/BZC42n1r/IMG_8852.gif","stickerMeaning":"老婆快吃药/拿着药丸狂奔","sender":"them","time":"10:21","timestamp":1776478901285,"roundId":"round_1776478858043_hgez39v39","generatedMode":false,"translation":null,"userId":"uid_1776442539116_4zqm7ieu5","characterId":"05011273-b4d1-4d44-9c23-b1403d71b6b8","_id":2157}]